reprlist/__init__.py
reprlist/_tools.py
reprlist/dev.py
reprlist/reprlist.py
reprlist/reprlist_old.py
reprlist/tools.py
reprlist.py-1.3.9.dist-info/LICENSE
reprlist.py-1.3.9.dist-info/METADATA
reprlist.py-1.3.9.dist-info/WHEEL
reprlist.py-1.3.9.dist-info/top_level.txt
reprlist.py-1.3.9.dist-info/RECORD
