Metadata-Version: 2.1
Name: reprlist.py
Version: 1.3.9
Summary: Create and edit multiline text(str), a tool to realize __repr__.
Home-page: UNKNOWN
Author: Juntong
Author-email: jessica_ye2015@sina.com.cn
License: MIT License
Keywords: repr multiline str char text
Platform: UNKNOWN
Classifier: Programming Language :: Python :: 3
Classifier: License :: OSI Approved :: MIT License
Classifier: Operating System :: OS Independent
License-File: LICENSE
